odoo10_addon_hr_timesheet_task_required-10.0.1.0.1-py2.7-nspkg.pth
odoo/addons/hr_timesheet_task_required/README.rst
odoo/addons/hr_timesheet_task_required/__init__.py
odoo/addons/hr_timesheet_task_required/__manifest__.py
odoo/addons/hr_timesheet_task_required/i18n/hr_timesheet_task_required.pot
odoo/addons/hr_timesheet_task_required/i18n/it.po
odoo/addons/hr_timesheet_task_required/static/description/icon.png
odoo/addons/hr_timesheet_task_required/static/src/js/hr_timesheet.js
odoo/addons/hr_timesheet_task_required/views/account_analytic_line.xml
odoo/addons/hr_timesheet_task_required/views/assets.xml
odoo/addons/hr_timesheet_task_required/views/hr_timesheet_sheet.xml
odoo10_addon_hr_timesheet_task_required-10.0.1.0.1.dist-info/METADATA
odoo10_addon_hr_timesheet_task_required-10.0.1.0.1.dist-info/RECORD
odoo10_addon_hr_timesheet_task_required-10.0.1.0.1.dist-info/WHEEL
odoo10_addon_hr_timesheet_task_required-10.0.1.0.1.dist-info/namespace_packages.txt
odoo10_addon_hr_timesheet_task_required-10.0.1.0.1.dist-info/top_level.txt
