Metadata-Version: 2.1
Name: odoo10-addon-hr-timesheet-task-required
Version: 10.0.1.0.1
Summary: Set task on timesheet as a mandatory field
Home-page: https://github.com/OCA/hr-timesheet
Author: ACSONE SA/NV, Odoo Community Association (OCA)
Author-email: support@odoo-community.org
License: AGPL-3
Platform: UNKNOWN
Classifier: Programming Language :: Python
Classifier: Framework :: Odoo
Classifier: License :: OSI Approved :: GNU Affero General Public License v3
Requires-Python: ~=2.7
Requires-Dist: odoo10-addon-hr-timesheet-task
Requires-Dist: odoo (<10.1dev,>=10.0)
